jsonconversion-1.2.1.dist-info/METADATA
jsonconversion-1.2.1.dist-info/WHEEL
jsonconversion-1.2.1.dist-info/entry_points.txt
jsonconversion-1.2.1.dist-info/licenses/LICENSE
jsonconversion/__init__.py
jsonconversion/conversion.py
jsonconversion/decoder.py
jsonconversion/encoder.py
jsonconversion/jsonobject.py
jsonconversion-1.2.1.dist-info/RECORD
