Metadata-Version: 2.1
Name: jsonconversion
Version: 1.2.1
Summary: This python module helps converting arbitrary Python objects into JSON strings and back.
Keywords: json,conversion,serialization
Author-Email: Franz Steinmetz <franz.steinmetz@dlr.de>, Johannes Ernst <j.ernst@dlr.de>
License: BSD
Classifier: Development Status :: 5 - Production/Stable
Classifier: Framework :: Flask
Classifier: Framework :: Django
Classifier: Intended Audience :: Developers
Classifier: Intended Audience :: Information Technology
Classifier: Intended Audience :: Science/Research
Classifier: License :: OSI Approved :: BSD License
Classifier: Operating System :: OS Independent
Classifier: Programming Language :: Python :: 2
Classifier: Programming Language :: Python :: 3
Classifier: Topic :: Internet :: WWW/HTTP
Classifier: Topic :: Scientific/Engineering :: Interface Engine/Protocol Translator
Classifier: Topic :: Software Development :: Libraries :: Python Modules
Classifier: Topic :: Software Development :: Object Brokering
Classifier: Topic :: Utilities
Project-URL: Homepage, https://github.com/DLR-RM/python-jsonconversion
Requires-Python: >=3.9
Requires-Dist: numpy<3.0,>=1.23
